potranslator/__init__.py
potranslator/basic.py
potranslator/commands.py
potranslator/potranslator.py
potranslator/pycompat.py
potranslator/supported_languages.json
potranslator/transifex.py
potranslator/locale_dir/__init__.py
potranslator/locale_dir/potranslator.pot
potranslator/locale_dir/af/LC_MESSAGES/potranslator.mo
potranslator/locale_dir/af/LC_MESSAGES/potranslator.po
potranslator/locale_dir/am/LC_MESSAGES/potranslator.mo
potranslator/locale_dir/am/LC_MESSAGES/potranslator.po
potranslator/locale_dir/ar/LC_MESSAGES/potranslator.mo
potranslator/locale_dir/ar/LC_MESSAGES/potranslator.po
potranslator/locale_dir/az/LC_MESSAGES/potranslator.mo
potranslator/locale_dir/az/LC_MESSAGES/potranslator.po
potranslator/locale_dir/be/LC_MESSAGES/potranslator.mo
potranslator/locale_dir/be/LC_MESSAGES/potranslator.po
potranslator/locale_dir/bg/LC_MESSAGES/potranslator.mo
potranslator/locale_dir/bg/LC_MESSAGES/potranslator.po
potranslator/locale_dir/bn/LC_MESSAGES/potranslator.mo
potranslator/locale_dir/bn/LC_MESSAGES/potranslator.po
potranslator/locale_dir/bs/LC_MESSAGES/potranslator.mo
potranslator/locale_dir/bs/LC_MESSAGES/potranslator.po
potranslator/locale_dir/ca/LC_MESSAGES/potranslator.mo
potranslator/locale_dir/ca/LC_MESSAGES/potranslator.po
potranslator/locale_dir/ceb/LC_MESSAGES/potranslator.mo
potranslator/locale_dir/ceb/LC_MESSAGES/potranslator.po
potranslator/locale_dir/co/LC_MESSAGES/potranslator.mo
potranslator/locale_dir/co/LC_MESSAGES/potranslator.po
potranslator/locale_dir/cs/LC_MESSAGES/potranslator.mo
potranslator/locale_dir/cs/LC_MESSAGES/potranslator.po
potranslator/locale_dir/cy/LC_MESSAGES/potranslator.mo
potranslator/locale_dir/cy/LC_MESSAGES/potranslator.po
potranslator/locale_dir/da/LC_MESSAGES/potranslator.mo
potranslator/locale_dir/da/LC_MESSAGES/potranslator.po
potranslator/locale_dir/de/LC_MESSAGES/potranslator.mo
potranslator/locale_dir/de/LC_MESSAGES/potranslator.po
potranslator-1.1.5.dist-info/DESCRIPTION.rst
potranslator-1.1.5.dist-info/METADATA
potranslator-1.1.5.dist-info/RECORD
potranslator-1.1.5.dist-info/WHEEL
potranslator-1.1.5.dist-info/entry_points.txt
potranslator-1.1.5.dist-info/metadata.json
potranslator-1.1.5.dist-info/top_level.txt
