Metadata-Version: 2.0
Name: potranslator
Version: 1.1.5
Summary: A python package to easily translate po and pot files in any language supported by Google Translate.
Home-page: https://github.com/SekouD/potranslator
Author: SekouD
Author-email: sekoud.python@gmail.com
License: BSD license
Keywords: potranslator sphinx sphinx-intl gettext localization translation translate po pot mo internationalization python google
Platform: UNKNOWN
Classifier: Development Status :: 5 - Production/Stable
Classifier: Topic :: Software Development :: Libraries :: Python Modules
Classifier: Topic :: Utilities
Classifier: Intended Audience :: Developers
Classifier: Intended Audience :: End Users/Desktop
Classifier: Intended Audience :: Education
Classifier: Intended Audience :: Science/Research
Classifier: Intended Audience :: Developers
Classifier: Intended Audience :: Information Technology
Classifier: License :: OSI Approved :: BSD License
Classifier: Operating System :: OS Independent
Classifier: Operating System :: MacOS
Classifier: Operating System :: Microsoft
Classifier: Operating System :: POSIX
Classifier: Natural Language :: Afrikaans
Classifier: Natural Language :: Arabic
Classifier: Natural Language :: German
Classifier: Natural Language :: Greek
Classifier: Natural Language :: English
Classifier: Natural Language :: French
Classifier: Natural Language :: Italian
Classifier: Natural Language :: Japanese
Classifier: Natural Language :: Chinese (Simplified)
Classifier: Programming Language :: Python :: 2
Classifier: Programming Language :: Python :: 2.7
Classifier: Programming Language :: Python :: 3
Classifier: Programming Language :: Python :: 3.4
Classifier: Programming Language :: Python :: 3.5
Classifier: Programming Language :: Python :: 3.6
Requires-Dist: Click (>=6.0)
Requires-Dist: googletrans (==2.3.0)
Requires-Dist: polib (==1.1.0)
Requires-Dist: path.py (==11.0.1)
Requires-Dist: importlib-resources (==1.0.1)
